imaugtools/__init__.py
imaugtools/crop_functions.py
imaugtools/helper_functions.py
imaugtools/rotate_functions.py
imaugtools/translate_functions.py
imaugtools-0.1.2.dist-info/LICENSE
imaugtools-0.1.2.dist-info/METADATA
imaugtools-0.1.2.dist-info/WHEEL
imaugtools-0.1.2.dist-info/top_level.txt
imaugtools-0.1.2.dist-info/RECORD
