Metadata-Version: 2.1
Name: imaugtools
Version: 0.1.2
Summary: imaugtools contains tools used for image augmentation: translate, rotate, crop. This library is for you if you do NOT want to stretch or skew, or pad pixels when doing any of these operations.
Home-page: https://github.com/saravanabalagi/imaugtools
Author: Saravanabalagi Ramachandran
Author-email: saravanabalagi@hotmail.com
License: MIT
Platform: UNKNOWN
Classifier: Development Status :: 5 - Production/Stable
Classifier: Topic :: Software Development :: Libraries
Classifier: License :: OSI Approved :: MIT License
Classifier: Programming Language :: Python :: 3
Classifier: Programming Language :: Python :: 3.6
Classifier: Programming Language :: Python :: 3.7
Classifier: Programming Language :: Python :: 3.8
Requires-Dist: numpy
Requires-Dist: opencv-python
